PyGitUp/__init__.py
PyGitUp/git_wrapper.py
PyGitUp/gitup.py
PyGitUp/utils.py
PyGitUp/tests/__init__.py
PyGitUp/tests/test_ahead_of_upstream.py
PyGitUp/tests/test_detached.py
PyGitUp/tests/test_diverged.py
PyGitUp/tests/test_fast_forwarded.py
PyGitUp/tests/test_faster_fastforwarded.py
PyGitUp/tests/test_fetch_fail.py
PyGitUp/tests/test_fetch_interrupted.py
PyGitUp/tests/test_fetch_large_output.py
PyGitUp/tests/test_fetchall.py
PyGitUp/tests/test_git_not_in_path.py
PyGitUp/tests/test_issue_55.py
PyGitUp/tests/test_local_tracking.py
PyGitUp/tests/test_log_hook.py
PyGitUp/tests/test_multiple_remotes.py
PyGitUp/tests/test_no_remotes.py
PyGitUp/tests/test_nofetch.py
PyGitUp/tests/test_not_on_a_git_repo.py
PyGitUp/tests/test_out_of_tree.py
PyGitUp/tests/test_overwrite_untracked_error.py
PyGitUp/tests/test_push.py
PyGitUp/tests/test_rebase_arguments.py
PyGitUp/tests/test_rebase_error.py
PyGitUp/tests/test_rebasing.py
PyGitUp/tests/test_remote_branch_deleted.py
PyGitUp/tests/test_returning_to_branch.py
PyGitUp/tests/test_run_in_subdir.py
PyGitUp/tests/test_separate_worktree.py
PyGitUp/tests/test_stash_error.py
PyGitUp/tests/test_submodules.py
PyGitUp/tests/test_submodules_dirty.py
PyGitUp/tests/test_tracking.py
PyGitUp/tests/test_unstash_error.py
PyGitUp/tests/test_up_to_date.py
PyGitUp/tests/test_utils.py
PyGitUp/tests/test_version.py
git_up-2.4.0.dist-info/METADATA
git_up-2.4.0.dist-info/WHEEL
git_up-2.4.0.dist-info/entry_points.txt
git_up-2.4.0.dist-info/licenses/LICENCE
git_up-2.4.0.dist-info/RECORD
