Metadata-Version: 2.4
Name: git-up
Version: 2.4.0
Summary: A python implementation of 'git up'
Project-URL: Homepage, https://github.com/msiemens/PyGitUp
Author-email: Markus Siemens <markus@m-siemens.de>
License-Expression: MIT
License-File: LICENCE
Keywords: database,nosql
Classifier: Development Status :: 5 - Production/Stable
Classifier: Environment :: Console
Classifier: Intended Audience :: Developers
Classifier: License :: OSI Approved :: MIT License
Classifier: Programming Language :: Python :: 3
Classifier: Programming Language :: Python :: 3.10
Classifier: Programming Language :: Python :: 3.11
Classifier: Programming Language :: Python :: 3.12
Classifier: Programming Language :: Python :: 3.13
Classifier: Programming Language :: Python :: 3.14
Classifier: Topic :: Software Development :: Version Control
Classifier: Topic :: Utilities
Requires-Python: <4,>=3.10
Requires-Dist: colorama~=0.4
Requires-Dist: gitpython~=3.1
Requires-Dist: packaging~=25.0
Requires-Dist: termcolor~=3.2
